[{"model": "admin.logentry", "pk": 1, "fields": {"action_time": "2023-07-20T17:45:28.148Z", "user": 1, "content_type": 6, "object_id": "36", "object_repr": "kevin.riley (Kevin Riley)", "action_flag": 3, "change_message": ""}}, {"model": "admin.logentry", "pk": 2, "fields": {"action_time": "2023-07-20T17:45:28.153Z", "user": 1, "content_type": 6, "object_id": "31", "object_repr": "lucas.ortega (Lucas Ortega)", "action_flag": 3, "change_message": ""}}, {"model": "admin.logentry", "pk": 3, "fields": {"action_time": "2023-07-20T17:45:28.157Z", "user": 1, "content_type": 6, "object_id": "14", "object_repr": "melanie.sanders (Melanie Sanders)", "action_flag": 3, "change_message": ""}}, {"model": "admin.logentry", "pk": 4, "fields": {"action_time": "2023-07-20T17:45:28.161Z", "user": 1, "content_type": 6, "object_id": "15", "object_repr": "michelle.simpson (Michelle Simpson)", "action_flag": 3, "change_message": ""}}, {"model": "admin.logentry", "pk": 5, "fields": {"action_time": "2023-07-20T17:45:28.165Z", "user": 1, "content_type": 6, "object_id": "38", "object_repr": "miguel.johnson (Miguel Johnson)", "action_flag": 3, "change_message": ""}}, {"model": "admin.logentry", "pk": 6, "fields": {"action_time": "2023-07-20T17:45:28.170Z", "user": 1, "content_type": 6, "object_id": "29", "object_repr": "nathan.robinson (Nathan Robinson)", "action_flag": 3, "change_message": ""}}, {"model": "admin.logentry", "pk": 7, "fields": {"action_time": "2023-07-20T17:45:28.174Z", "user": 1, "content_type": 6, "object_id": "35", "object_repr": "nicole.parker (Nicole Parker)", "action_flag": 3, "change_message": ""}}, {"model": "admin.logentry", "pk": 8, "fields": {"action_time": "2023-07-20T17:45:28.178Z", "user": 1, "content_type": 6, "object_id": "9", "object_repr": "olivia.rivers (Olivia Rivers)", "action_flag": 3, "change_message": ""}}, {"model": "admin.logentry", "pk": 9, "fields": {"action_time": "2023-07-20T17:45:28.182Z", "user": 1, "content_type": 6, "object_id": "10", "object_repr": "paige.nelson (Paige Nelson)", "action_flag": 3, "change_message": ""}}, {"model": "admin.logentry", "pk": 10, "fields": {"action_time": "2023-07-20T17:45:28.186Z", "user": 1, "content_type": 6, "object_id": "25", "object_repr": "paul.wilson (Paul Wilson)", "action_flag": 3, "change_message": ""}}, {"model": "admin.logentry", "pk": 11, "fields": {"action_time": "2023-07-20T17:45:28.190Z", "user": 1, "content_type": 6, "object_id": "17", "object_repr": "phillip.rivera (Phillip Rivera)", "action_flag": 3, "change_message": ""}}, {"model": "admin.logentry", "pk": 12, "fields": {"action_time": "2023-07-20T17:45:28.194Z", "user": 1, "content_type": 6, "object_id": "39", "object_repr": "robin.tanner (Robin Tanner)", "action_flag": 3, "change_message": ""}}, {"model": "admin.logentry", "pk": 13, "fields": {"action_time": "2023-07-20T17:45:28.198Z", "user": 1, "content_type": 6, "object_id": "11", "object_repr": "steven.brown (Steven Brown)", "action_flag": 3, "change_message": ""}}, {"model": "admin.logentry", "pk": 14, "fields": {"action_time": "2023-07-20T17:45:28.202Z", "user": 1, "content_type": 6, "object_id": "24", "object_repr": "terri.fisher (Terri Fisher)", "action_flag": 3, "change_message": ""}}, {"model": "admin.logentry", "pk": 15, "fields": {"action_time": "2023-07-20T17:45:28.206Z", "user": 1, "content_type": 6, "object_id": "28", "object_repr": "terry.knapp (Terry Knapp)", "action_flag": 3, "change_message": ""}}, {"model": "admin.logentry", "pk": 16, "fields": {"action_time": "2023-07-20T17:45:28.210Z", "user": 1, "content_type": 6, "object_id": "27", "object_repr": "tiffany.graham (Tiffany Graham)", "action_flag": 3, "change_message": ""}}, {"model": "admin.logentry", "pk": 17, "fields": {"action_time": "2023-07-20T17:45:28.214Z", "user": 1, "content_type": 6, "object_id": "4", "object_repr": "tommy.santiago (Tommy Santiago)", "action_flag": 3, "change_message": ""}}, {"model": "admin.logentry", "pk": 18, "fields": {"action_time": "2023-07-20T17:45:28.218Z", "user": 1, "content_type": 6, "object_id": "33", "object_repr": "willie.holland (Willie Holland)", "action_flag": 3, "change_message": ""}}, {"model": "admin.logentry", "pk": 19, "fields": {"action_time": "2023-07-20T17:45:28.226Z", "user": 1, "content_type": 6, "object_id": "19", "object_repr": "zachary.gonzalez (Zachary Gonzalez)", "action_flag": 3, "change_message": ""}}, {"model": "admin.logentry", "pk": 20, "fields": {"action_time": "2023-07-20T17:45:28.230Z", "user": 1, "content_type": 6, "object_id": "32", "object_repr": "zachary.love (Zachary Love)", "action_flag": 3, "change_message": ""}}, {"model": "admin.logentry", "pk": 21, "fields": {"action_time": "2023-07-20T17:48:31.624Z", "user": 1, "content_type": 7, "object_id": "1", "object_repr": "Main Courses", "action_flag": 1, "change_message": "[{\"added\": {}}]"}}, {"model": "admin.logentry", "pk": 22, "fields": {"action_time": "2023-07-20T17:48:50.702Z", "user": 1, "content_type": 7, "object_id": "2", "object_repr": "Salads", "action_flag": 1, "change_message": "[{\"added\": {}}]"}}, {"model": "admin.logentry", "pk": 23, "fields": {"action_time": "2023-07-20T17:48:59.628Z", "user": 1, "content_type": 7, "object_id": "3", "object_repr": "Appetizers", "action_flag": 1, "change_message": "[{\"added\": {}}]"}}, {"model": "admin.logentry", "pk": 24, "fields": {"action_time": "2023-07-20T17:49:05.513Z", "user": 1, "content_type": 7, "object_id": "4", "object_repr": "Soups", "action_flag": 1, "change_message": "[{\"added\": {}}]"}}, {"model": "admin.logentry", "pk": 25, "fields": {"action_time": "2023-07-20T17:49:10.600Z", "user": 1, "content_type": 7, "object_id": "5", "object_repr": "Pasta", "action_flag": 1, "change_message": "[{\"added\": {}}]"}}, {"model": "admin.logentry", "pk": 26, "fields": {"action_time": "2023-07-20T17:49:14.375Z", "user": 1, "content_type": 7, "object_id": "6", "object_repr": "Pizza", "action_flag": 1, "change_message": "[{\"added\": {}}]"}}, {"model": "admin.logentry", "pk": 27, "fields": {"action_time": "2023-07-20T17:49:17.094Z", "user": 1, "content_type": 7, "object_id": "7", "object_repr": "Sandwiches", "action_flag": 1, "change_message": "[{\"added\": {}}]"}}, {"model": "admin.logentry", "pk": 28, "fields": {"action_time": "2023-07-20T17:49:19.789Z", "user": 1, "content_type": 7, "object_id": "8", "object_repr": "Burgers", "action_flag": 1, "change_message": "[{\"added\": {}}]"}}, {"model": "admin.logentry", "pk": 29, "fields": {"action_time": "2023-07-20T17:49:25.906Z", "user": 1, "content_type": 7, "object_id": "9", "object_repr": "Seafood", "action_flag": 1, "change_message": "[{\"added\": {}}]"}}, {"model": "admin.logentry", "pk": 30, "fields": {"action_time": "2023-07-20T17:49:28.682Z", "user": 1, "content_type": 7, "object_id": "10", "object_repr": "Steaks", "action_flag": 1, "change_message": "[{\"added\": {}}]"}}, {"model": "admin.logentry", "pk": 31, "fields": {"action_time": "2023-07-20T17:49:31.891Z", "user": 1, "content_type": 7, "object_id": "11", "object_repr": "Sushi", "action_flag": 1, "change_message": "[{\"added\": {}}]"}}, {"model": "admin.logentry", "pk": 32, "fields": {"action_time": "2023-07-20T17:49:44.720Z", "user": 1, "content_type": 7, "object_id": "12", "object_repr": "Vegan Dishes", "action_flag": 1, "change_message": "[{\"added\": {}}]"}}, {"model": "admin.logentry", "pk": 33, "fields": {"action_time": "2023-07-20T17:49:51.306Z", "user": 1, "content_type": 7, "object_id": "13", "object_repr": "Noodles", "action_flag": 1, "change_message": "[{\"added\": {}}]"}}, {"model": "admin.logentry", "pk": 34, "fields": {"action_time": "2023-07-20T17:50:13.362Z", "user": 1, "content_type": 7, "object_id": "14", "object_repr": "Desserts", "action_flag": 1, "change_message": "[{\"added\": {}}]"}}, {"model": "admin.logentry", "pk": 35, "fields": {"action_time": "2023-07-20T17:50:39.404Z", "user": 1, "content_type": 7, "object_id": "15", "object_repr": "Breakfast", "action_flag": 1, "change_message": "[{\"added\": {}}]"}}, {"model": "admin.logentry", "pk": 36, "fields": {"action_time": "2023-07-20T17:50:46.791Z", "user": 1, "content_type": 7, "object_id": "16", "object_repr": "Cocktails", "action_flag": 1, "change_message": "[{\"added\": {}}]"}}, {"model": "admin.logentry", "pk": 37, "fields": {"action_time": "2023-07-20T17:50:59.204Z", "user": 1, "content_type": 7, "object_id": "16", "object_repr": "Cocktails", "action_flag": 3, "change_message": ""}}, {"model": "admin.logentry", "pk": 38, "fields": {"action_time": "2023-07-20T18:23:26.801Z", "user": 1, "content_type": 8, "object_id": "1", "object_repr": "Mozzarella Sticks", "action_flag": 1, "change_message": "[{\"added\": {}}]"}}, {"model": "admin.logentry", "pk": 39, "fields": {"action_time": "2023-07-20T18:23:52.850Z", "user": 1, "content_type": 8, "object_id": "2", "object_repr": "Bruschetta", "action_flag": 1, "change_message": "[{\"added\": {}}]"}}, {"model": "admin.logentry", "pk": 40, "fields": {"action_time": "2023-07-20T18:25:31.826Z", "user": 1, "content_type": 8, "object_id": "3", "object_repr": "Shrimp Cocktail", "action_flag": 1, "change_message": "[{\"added\": {}}]"}}, {"model": "admin.logentry", "pk": 41, "fields": {"action_time": "2023-07-20T18:26:12.611Z", "user": 1, "content_type": 8, "object_id": "4", "object_repr": "Caesar Salad", "action_flag": 1, "change_message": "[{\"added\": {}}]"}}, {"model": "admin.logentry", "pk": 42, "fields": {"action_time": "2023-07-20T18:26:35.614Z", "user": 1, "content_type": 8, "object_id": "5", "object_repr": "Greek Salad", "action_flag": 1, "change_message": "[{\"added\": {}}]"}}, {"model": "admin.logentry", "pk": 43, "fields": {"action_time": "2023-07-20T18:26:54.608Z", "user": 1, "content_type": 8, "object_id": "6", "object_repr": "Caprese Salad", "action_flag": 1, "change_message": "[{\"added\": {}}]"}}, {"model": "admin.logentry", "pk": 44, "fields": {"action_time": "2023-07-20T18:28:17.095Z", "user": 1, "content_type": 8, "object_id": "7", "object_repr": "Tomato Basil Soup", "action_flag": 1, "change_message": "[{\"added\": {}}]"}}, {"model": "admin.logentry", "pk": 45, "fields": {"action_time": "2023-07-20T18:28:39.314Z", "user": 1, "content_type": 8, "object_id": "8", "object_repr": "Minestrone Soup", "action_flag": 1, "change_message": "[{\"added\": {}}]"}}, {"model": "admin.logentry", "pk": 46, "fields": {"action_time": "2023-07-20T18:29:07.272Z", "user": 1, "content_type": 8, "object_id": "9", "object_repr": "Chicken Noodle Soup", "action_flag": 1, "change_message": "[{\"added\": {}}]"}}, {"model": "admin.logentry", "pk": 47, "fields": {"action_time": "2023-07-20T18:29:30.766Z", "user": 1, "content_type": 8, "object_id": "10", "object_repr": "French Onion Soup", "action_flag": 1, "change_message": "[{\"added\": {}}]"}}, {"model": "admin.logentry", "pk": 48, "fields": {"action_time": "2023-07-20T18:31:16.917Z", "user": 1, "content_type": 8, "object_id": "11", "object_repr": "Roast Duck", "action_flag": 1, "change_message": "[{\"added\": {}}]"}}, {"model": "admin.logentry", "pk": 49, "fields": {"action_time": "2023-07-20T18:31:46.569Z", "user": 1, "content_type": 8, "object_id": "12", "object_repr": "Pan-Seared Salmon", "action_flag": 1, "change_message": "[{\"added\": {}}]"}}, {"model": "admin.logentry", "pk": 50, "fields": {"action_time": "2023-07-20T18:32:16.756Z", "user": 1, "content_type": 8, "object_id": "13", "object_repr": "Grilled Chicken Breast", "action_flag": 1, "change_message": "[{\"added\": {}}]"}}, {"model": "admin.logentry", "pk": 51, "fields": {"action_time": "2023-07-20T18:34:04.543Z", "user": 1, "content_type": 8, "object_id": "14", "object_repr": "Lasagna", "action_flag": 1, "change_message": "[{\"added\": {}}]"}}, {"model": "admin.logentry", "pk": 52, "fields": {"action_time": "2023-07-20T18:34:40.988Z", "user": 1, "content_type": 8, "object_id": "15", "object_repr": "Spaghetti Carbonara", "action_flag": 1, "change_message": "[{\"added\": {}}]"}}, {"model": "admin.logentry", "pk": 53, "fields": {"action_time": "2023-07-20T18:35:08.225Z", "user": 1, "content_type": 8, "object_id": "16", "object_repr": "Fettuccine Alfredo", "action_flag": 1, "change_message": "[{\"added\": {}}]"}}, {"model": "admin.logentry", "pk": 54, "fields": {"action_time": "2023-07-20T18:36:25.887Z", "user": 1, "content_type": 8, "object_id": "17", "object_repr": "Margherita Pizza", "action_flag": 1, "change_message": "[{\"added\": {}}]"}}, {"model": "admin.logentry", "pk": 55, "fields": {"action_time": "2023-07-20T18:36:51.155Z", "user": 1, "content_type": 8, "object_id": "18", "object_repr": "Pepperoni Pizza", "action_flag": 1, "change_message": "[{\"added\": {}}]"}}, {"model": "admin.logentry", "pk": 56, "fields": {"action_time": "2023-07-20T18:37:10.855Z", "user": 1, "content_type": 8, "object_id": "19", "object_repr": "Hawaiian Pizza", "action_flag": 1, "change_message": "[{\"added\": {}}]"}}, {"model": "admin.logentry", "pk": 57, "fields": {"action_time": "2023-07-20T18:38:02.957Z", "user": 1, "content_type": 8, "object_id": "20", "object_repr": "BBQ Chicken Pizza", "action_flag": 1, "change_message": "[{\"added\": {}}]"}}, {"model": "admin.logentry", "pk": 58, "fields": {"action_time": "2023-07-20T18:41:38.236Z", "user": 1, "content_type": 8, "object_id": "21", "object_repr": "Grilled Cheese Sandwich", "action_flag": 1, "change_message": "[{\"added\": {}}]"}}, {"model": "admin.logentry", "pk": 59, "fields": {"action_time": "2023-07-20T18:42:35.914Z", "user": 1, "content_type": 8, "object_id": "22", "object_repr": "Reuben Sandwich", "action_flag": 1, "change_message": "[{\"added\": {}}]"}}, {"model": "admin.logentry", "pk": 60, "fields": {"action_time": "2023-07-20T18:42:57.761Z", "user": 1, "content_type": 8, "object_id": "23", "object_repr": "BLT Sandwich", "action_flag": 1, "change_message": "[{\"added\": {}}]"}}, {"model": "admin.logentry", "pk": 61, "fields": {"action_time": "2023-07-20T18:43:29.850Z", "user": 1, "content_type": 8, "object_id": "24", "object_repr": "Classic Cheeseburger", "action_flag": 1, "change_message": "[{\"added\": {}}]"}}, {"model": "admin.logentry", "pk": 62, "fields": {"action_time": "2023-07-20T18:43:50.553Z", "user": 1, "content_type": 8, "object_id": "25", "object_repr": "BBQ Bacon Burger", "action_flag": 1, "change_message": "[{\"added\": {}}]"}}, {"model": "admin.logentry", "pk": 63, "fields": {"action_time": "2023-07-20T18:44:09.061Z", "user": 1, "content_type": 8, "object_id": "26", "object_repr": "Hawaiian Teriyaki Burger", "action_flag": 1, "change_message": "[{\"added\": {}}]"}}, {"model": "admin.logentry", "pk": 64, "fields": {"action_time": "2023-07-20T18:44:46.923Z", "user": 1, "content_type": 8, "object_id": "27", "object_repr": "Bacon Mushroom Swiss Burger", "action_flag": 1, "change_message": "[{\"added\": {}}]"}}, {"model": "admin.logentry", "pk": 65, "fields": {"action_time": "2023-07-20T18:45:57.273Z", "user": 1, "content_type": 8, "object_id": "28", "object_repr": "Lobster Tail", "action_flag": 1, "change_message": "[{\"added\": {}}]"}}, {"model": "admin.logentry", "pk": 66, "fields": {"action_time": "2023-07-20T18:46:30.314Z", "user": 1, "content_type": 8, "object_id": "29", "object_repr": "Garlic Butter Shrimp", "action_flag": 1, "change_message": "[{\"added\": {}}]"}}, {"model": "admin.logentry", "pk": 67, "fields": {"action_time": "2023-07-20T18:47:00.747Z", "user": 1, "content_type": 8, "object_id": "30", "object_repr": "Blackened Red Snapper", "action_flag": 1, "change_message": "[{\"added\": {}}]"}}, {"model": "admin.logentry", "pk": 68, "fields": {"action_time": "2023-07-20T18:47:35.579Z", "user": 1, "content_type": 8, "object_id": "31", "object_repr": "Grilled Mahi Mahi", "action_flag": 1, "change_message": "[{\"added\": {}}]"}}, {"model": "admin.logentry", "pk": 69, "fields": {"action_time": "2023-07-20T18:48:25.701Z", "user": 1, "content_type": 8, "object_id": "32", "object_repr": "Seared Scallops", "action_flag": 1, "change_message": "[{\"added\": {}}]"}}, {"model": "admin.logentry", "pk": 70, "fields": {"action_time": "2023-07-20T18:49:52.788Z", "user": 1, "content_type": 8, "object_id": "33", "object_repr": "Filet Mignon", "action_flag": 1, "change_message": "[{\"added\": {}}]"}}, {"model": "admin.logentry", "pk": 71, "fields": {"action_time": "2023-07-20T18:50:15.936Z", "user": 1, "content_type": 8, "object_id": "34", "object_repr": "Ribeye Steak", "action_flag": 1, "change_message": "[{\"added\": {}}]"}}, {"model": "admin.logentry", "pk": 72, "fields": {"action_time": "2023-07-20T18:50:41.966Z", "user": 1, "content_type": 8, "object_id": "35", "object_repr": "New York Strip Steak", "action_flag": 1, "change_message": "[{\"added\": {}}]"}}, {"model": "admin.logentry", "pk": 73, "fields": {"action_time": "2023-07-20T18:51:08.479Z", "user": 1, "content_type": 8, "object_id": "36", "object_repr": "T-Bone Steak", "action_flag": 1, "change_message": "[{\"added\": {}}]"}}, {"model": "admin.logentry", "pk": 74, "fields": {"action_time": "2023-07-20T18:51:35.791Z", "user": 1, "content_type": 8, "object_id": "37", "object_repr": "California Roll", "action_flag": 1, "change_message": "[{\"added\": {}}]"}}, {"model": "admin.logentry", "pk": 75, "fields": {"action_time": "2023-07-20T18:51:55.206Z", "user": 1, "content_type": 8, "object_id": "38", "object_repr": "Spicy Tuna Roll", "action_flag": 1, "change_message": "[{\"added\": {}}]"}}, {"model": "admin.logentry", "pk": 76, "fields": {"action_time": "2023-07-20T18:52:19.963Z", "user": 1, "content_type": 8, "object_id": "39", "object_repr": "Shrimp Tempura Roll", "action_flag": 1, "change_message": "[{\"added\": {}}]"}}, {"model": "admin.logentry", "pk": 77, "fields": {"action_time": "2023-07-20T18:52:42.623Z", "user": 1, "content_type": 8, "object_id": "40", "object_repr": "Rainbow Roll", "action_flag": 1, "change_message": "[{\"added\": {}}]"}}, {"model": "admin.logentry", "pk": 78, "fields": {"action_time": "2023-07-20T18:53:34.527Z", "user": 1, "content_type": 8, "object_id": "41", "object_repr": "New York Cheesecake", "action_flag": 1, "change_message": "[{\"added\": {}}]"}}, {"model": "admin.logentry", "pk": 79, "fields": {"action_time": "2023-07-20T18:53:55.569Z", "user": 1, "content_type": 8, "object_id": "42", "object_repr": "Tiramisu", "action_flag": 1, "change_message": "[{\"added\": {}}]"}}, {"model": "admin.logentry", "pk": 80, "fields": {"action_time": "2023-07-20T18:54:12.480Z", "user": 1, "content_type": 8, "object_id": "43", "object_repr": 